googlescrape
