Metadata-Version: 2.1
Name: googlescrape
Version: 1.0.0
Summary: This is a python api to scrape search results from a url.
Home-page: https://github.com/JavaProgswing/googlescrape
Author: JavaProgswing
Author-email: thejavaprofessional@gmail.com
License: MIT
Keywords: googlescrape
Platform: UNKNOWN
Classifier: Development Status :: 5 - Production/Stable
Classifier: Intended Audience :: Developers
Classifier: Operating System :: OS Independent
Classifier: License :: OSI Approved :: MIT License
Classifier: Programming Language :: Python :: 3
License-File: LICENSE.txt
